Metadata-Version: 2.1
Name: eaf_base_api-async
Version: 2.2.1
Summary: A base API for EchterAlsFake's Porn APIs
Home-page: https://github.com/EchterAlsFake/eaf_base_api
Author: Johannes Habel
Author-email: EchterAlsFake@proton.me
License: LGPLv3
Classifier: License :: OSI Approved :: GNU Lesser General Public License v3 (LGPLv3)
Classifier: Programming Language :: Python
License-File: LICENSE
Requires-Dist: ffmpeg-progress-yield
Requires-Dist: m3u8
Requires-Dist: httpx
